cssdotpy/__init__.py
cssdotpy/addclass.py
cssdotpy/addelement.py
cssdotpy/addevent.py
cssdotpy/license.py
cssdotpy/main.py
CSSdotPy-0.1.dist-info/LICENSE
CSSdotPy-0.1.dist-info/METADATA
CSSdotPy-0.1.dist-info/WHEEL
CSSdotPy-0.1.dist-info/top_level.txt
CSSdotPy-0.1.dist-info/RECORD
