Metadata-Version: 2.1
Name: CSSdotPy
Version: 0.1
Summary: A way of writing CSS with a Python library.
Home-page: https://github.com/BLUEAMETHYST-Studios/CSS.py
Author: BLUEAMETHYST Studios
License: GNU GENERAL PUBLIC LICENSE VERSION 3
Keywords: css,open-source
Classifier: Development Status :: 3 - Alpha
Classifier: License :: OSI Approved :: GNU General Public License v3 (GPLv3)
Classifier: Operating System :: Microsoft :: Windows
Classifier: Operating System :: POSIX :: Linux
Classifier: Programming Language :: Python
Classifier: Programming Language :: Python :: 3
Classifier: Topic :: Text Processing
License-File: LICENSE
